gtmarket/__init__.py
gtmarket/api.py
gtmarket/core.py
gtmarket/predictor.py
gtmarket/version.py
gtmarket/tests/__init__.py
gtmarket/tests/test_predictor.py
gtmarket/tests/tests.py
gtmarket-0.1.7.dist-info/LICENSE
gtmarket-0.1.7.dist-info/METADATA
gtmarket-0.1.7.dist-info/WHEEL
gtmarket-0.1.7.dist-info/top_level.txt
gtmarket-0.1.7.dist-info/RECORD
