Metadata-Version: 2.1
Name: gtmarket
Version: 0.1.7
Summary: A collection of tools to work with go-to-market data
Home-page: https://github.com/robdmc/gtmarket
Author: Rob deCarvalho
Author-email: unlisted@unlisted.net
License: MIT
Classifier: Programming Language :: Python :: 3.7
Classifier: Intended Audience :: Developers
Classifier: License :: OSI Approved :: MIT License
Classifier: Operating System :: OS Independent
License-File: LICENSE
Provides-Extra: dev
